ca_certificates/__init__.py
ptxcompiler-0.0.0.dist-info/METADATA
ptxcompiler-0.0.0.dist-info/WHEEL
ptxcompiler-0.0.0.dist-info/top_level.txt
ptxcompiler-0.0.0.dist-info/RECORD
