Metadata-Version: 2.4
Name: ptxcompiler
Version: 0.0.0
Summary: Dummy ptxcompiler package for PyPI
Author-email: Your Name <you@example.com>
Requires-Python: >=3.7
